huscy/pseudonyms/__init__.py
huscy/pseudonyms/apps.py
huscy/pseudonyms/models.py
huscy/pseudonyms/services.py
huscy/pseudonyms/migrations/0001_initial.py
huscy/pseudonyms/migrations/__init__.py
huscy.pseudonyms-1.2.2.dist-info/LICENSE
huscy.pseudonyms-1.2.2.dist-info/METADATA
huscy.pseudonyms-1.2.2.dist-info/WHEEL
huscy.pseudonyms-1.2.2.dist-info/top_level.txt
huscy.pseudonyms-1.2.2.dist-info/RECORD
